vshock/__init__.py
vshock/__main__.py
vshock/cli.py
vshock/io.py
vshock/server.py
vshock/assets/ui/index.html
vshock/assets/ui/javascript/vshock.js
vshock-0.1.1.dist-info/LICENSE
vshock-0.1.1.dist-info/METADATA
vshock-0.1.1.dist-info/WHEEL
vshock-0.1.1.dist-info/entry_points.txt
vshock-0.1.1.dist-info/top_level.txt
vshock-0.1.1.dist-info/RECORD
